sardem/__init__.py
sardem/cli.py
sardem/constants.py
sardem/conversions.py
sardem/cop_dem.py
sardem/dem.py
sardem/download.py
sardem/loading.py
sardem/upsample.py
sardem/utils.py
sardem-0.11.3.dist-info/LICENSE
sardem-0.11.3.dist-info/METADATA
sardem-0.11.3.dist-info/WHEEL
sardem-0.11.3.dist-info/entry_points.txt
sardem-0.11.3.dist-info/top_level.txt
sardem-0.11.3.dist-info/RECORD
