Metadata-Version: 2.1
Name: sardem
Version: 0.11.3
Summary: Create upsampled DEMs for InSAR processing
Home-page: https://github.com/scottstanie/sardem
Author: Scott Staniewicz
Author-email: scott.stanie@gmail.com
Classifier: Programming Language :: Python
Classifier: Programming Language :: Python :: 2.7
Classifier: Programming Language :: Python :: 3.3
Classifier: Programming Language :: Python :: 3.4
Classifier: Programming Language :: Python :: 3.5
Classifier: Programming Language :: Python :: 3.6
Classifier: License :: OSI Approved :: MIT License
Classifier: Topic :: Scientific/Engineering
Classifier: Intended Audience :: Science/Research
License-File: LICENSE
Requires-Dist: numpy
Requires-Dist: requests
